[{"cost": 2.4, "nodes": ["G", "H"], "sequence_number": 83}, {"cost": 2.8, "nodes": ["G", "I"], "sequence_number": 83}, {"cost": 4.1, "nodes": ["G", "J"], "sequence_number": 83}, {"cost": 3.1, "nodes": ["B", "E"], "sequence_number": 7}, {"cost": Infinity, "nodes": ["C", "B"], "sequence_number": 12}, {"cost": Infinity, "nodes": ["A", "B"], "sequence_number": 12}, {"cost": Infinity, "nodes": ["I", "D"], "sequence_number": 70}, {"cost": Infinity, "nodes": ["H", "A"], "sequence_number": 56}, {"cost": Infinity, "nodes": ["H", "C"], "sequence_number": 56}, {"cost": Infinity, "nodes": ["H", "D"], "sequence_number": 56}, {"cost": Infinity, "nodes": ["F", "B"], "sequence_number": 60}, {"cost": Infinity, "nodes": ["F", "D"], "sequence_number": 60}, {"cost": 1.6, "nodes": ["H", "F"], "sequence_number": 62}, {"cost": Infinity, "nodes": ["J", "A"], "sequence_number": 71}, {"cost": 1.6, "nodes": ["J", "I"], "sequence_number": 71}]